modbus2websocket/__init__.py
modbus2websocket/async_modbus_client.py
modbus2websocket/async_modbus_server.py
modbus2websocket/async_websocket_server.py
modbus2websocket/router.py
modbus2websocket-0.0.5.dist-info/LICENSE
modbus2websocket-0.0.5.dist-info/METADATA
modbus2websocket-0.0.5.dist-info/WHEEL
modbus2websocket-0.0.5.dist-info/top_level.txt
modbus2websocket-0.0.5.dist-info/RECORD
