Metadata-Version: 2.1
Name: modbus2websocket
Version: 0.0.5
Summary: Modbus/TCP to websocket router.
Home-page: https://github.com/PakshNina/modbus2websocket
Author: Nina Pakshina
Author-email: ninucium@gmail.com
License: MIT
Keywords: modbus tcp websocket asyncio socket
Platform: UNKNOWN
Classifier: Programming Language :: Python :: 3
Classifier: License :: OSI Approved :: MIT License
Classifier: Operating System :: OS Independent
Requires-Dist: pyModbusTCP
Requires-Dist: websockets
